{"formatVersion":1,"histograms":{"stats":[{"basesPerBin":"20000","max":8,"mean":3.81896551724138},{"mean":7.11206896551724,"max":12,"basesPerBin":"40000"},{"mean":16.8936170212766,"basesPerBin":"100000","max":24}],"meta":[{"basesPerBin":"20000","arrayParams":{"chunkSize":10000,"length":232,"urlTemplate":"hist-20000-{Chunk}.json"}},{"basesPerBin":"40000","arrayParams":{"length":116,"chunkSize":10000,"urlTemplate":"hist-40000-{Chunk}.json"}},{"basesPerBin":"100000","arrayParams":{"chunkSize":10000,"length":47,"urlTemplate":"hist-100000-{Chunk}.json"}}]},"featureCount":764,"intervals":{"maxEnd":4636143,"classes":[{"isArrayAttr":{"Names":1},"attributes":["Start","End","Strand","Names","Id","Type","Seq_id","Source"]},{"attributes":["Start","End","Strand","Id","Type","Seq_id","Source","Names"],"isArrayAttr":{"Names":1}},{"attributes":["Start","End","Strand","Source","Seq_id","Type","Id","Names"],"isArrayAttr":{"Names":1}},{"isArrayAttr":{"Names":1},"attributes":["Start","End","Strand","Names","Seq_id","Source","Type","Id"]},{"attributes":["Start","End","Strand","Names","Id","Type","Source","Seq_id"],"isArrayAttr":{"Names":1}},{"isArrayAttr":{"Names":1},"attributes":["Start","End","Strand","Type","Id","Seq_id","Source","Names"]},{"isArrayAttr":{"Names":1},"attributes":["Start","End","Strand","Names","Id","Type","Seq_id","Source"]},{"isArrayAttr":{"Names":1},"attributes":["Start","End","Strand","Source","Seq_id","Type","Id","Names"]},{"isArrayAttr":{"Names":1},"attributes":["Start","End","Strand","Names","Type","Id","Seq_id","Source"]},{"isArrayAttr":{"Names":1},"attributes":["Start","End","Strand","Names","Source","Seq_id","Id","Type"]},{"isArrayAttr":{"Names":1},"attributes":["Start","End","Strand","Names","Source","Seq_id","Type","Id"]},{"attributes":["Start","End","Strand","Names","Seq_id","Source","Id","Type"],"isArrayAttr":{"Names":1}},{"isArrayAttr":{"Names":1},"attributes":["Start","End","Strand","Source","Seq_id","Id","Type","Names"]},{"isArrayAttr":{"Names":1},"attributes":["Start","End","Strand","Names","Id","Type","Source","Seq_id"]},{"attributes":["Start","End","Strand","Type","Id","Source","Seq_id","Names"],"isArrayAttr":{"Names":1}},{"attributes":["Start","End","Strand","Seq_id","Source","Id","Type","Names"],"isArrayAttr":{"Names":1}},{"isArrayAttr":{"Names":1},"attributes":["Start","End","Strand","Names","Seq_id","Source","Id","Type"]},{"attributes":["Start","End","Strand","Id","Type","Source","Seq_id","Names"],"isArrayAttr":{"Names":1}},{"isArrayAttr":{"Names":1},"attributes":["Start","End","Strand","Seq_id","Source","Id","Type","Names"]},{"isArrayAttr":{"Names":1},"attributes":["Start","End","Strand","Seq_id","Source","Type","Id","Names"]},{"attributes":["Start","End","Strand","Seq_id","Source","Type","Id","Names"],"isArrayAttr":{"Names":1}},{"attributes":["Start","End","Strand","Source","Seq_id","Id","Type","Names"],"isArrayAttr":{"Names":1}},{"attributes":["Start","End","Strand","Names","Seq_id","Source","Type","Id"],"isArrayAttr":{"Names":1}},{"isArrayAttr":{"Names":1},"attributes":["Start","End","Strand","Names","Source","Seq_id","Id","Type"]},{"isArrayAttr":{"Names":1},"attributes":["Start","End","Strand","Id","Type","Source","Seq_id","Names"]},{"isArrayAttr":{"Names":1},"attributes":["Start","End","Strand","Names","Source","Seq_id","Type","Id"]},{"isArrayAttr":{"Names":1},"attributes":["Start","End","Strand","Names","Type","Id","Source","Seq_id"]},{"isArrayAttr":{"Names":1},"attributes":["Start","End","Strand","Type","Id","Source","Seq_id","Names"]},{"isArrayAttr":{"Names":1},"attributes":["Start","End","Strand","Names","Type","Id","Seq_id","Source"]},{"isArrayAttr":{"Names":1},"attributes":["Start","End","Strand","Names","Type","Id","Source","Seq_id"]},{"attributes":["Start","End","Strand","Id","Type","Seq_id","Source","Names"],"isArrayAttr":{"Names":1}},{"attributes":["Start","End","Strand","Type","Id","Seq_id","Source","Names"],"isArrayAttr":{"Names":1}},{"attributes":["Start","End","Chunk"],"isArrayAttr":{"Sublist":1}}],"count":764,"urlTemplate":"lf-{Chunk}.json","lazyClass":32,"minStart":336,"nclist":[[32,336,3661550,1],[32,3683722,4636143,2]]}}