{"formatVersion":1,"featureCount":582,"histograms":{"meta":[{"arrayParams":{"urlTemplate":"hist-20000-{Chunk}.json","length":183,"chunkSize":10000},"basesPerBin":"20000"},{"basesPerBin":"40000","arrayParams":{"chunkSize":10000,"length":92,"urlTemplate":"hist-40000-{Chunk}.json"}}],"stats":[{"max":9,"basesPerBin":"20000","mean":3.53551912568306},{"basesPerBin":"40000","max":11,"mean":6.67391304347826}]},"intervals":{"classes":[{"isArrayAttr":{"Names":1},"attributes":["Start","End","Strand","Names","Id","Seq_id","Source","Type"]},{"attributes":["Start","End","Strand","Names","Id","Seq_id","Source","Type"],"isArrayAttr":{"Names":1}},{"attributes":["Start","End","Strand","Source","Type","Seq_id","Id","Names"],"isArrayAttr":{"Names":1}},{"isArrayAttr":{"Names":1},"attributes":["Start","End","Strand","Seq_id","Source","Type","Names","Id"]},{"isArrayAttr":{"Names":1},"attributes":["Start","End","Strand","Seq_id","Type","Source","Names","Id"]},{"isArrayAttr":{"Names":1},"attributes":["Start","End","Strand","Id","Names","Type","Source","Seq_id"]},{"isArrayAttr":{"Names":1},"attributes":["Start","End","Strand","Source","Type","Seq_id","Id","Names"]},{"attributes":["Start","End","Strand","Seq_id","Type","Source","Names","Id"],"isArrayAttr":{"Names":1}},{"isArrayAttr":{"Names":1},"attributes":["Start","End","Strand","Type","Source","Seq_id","Id","Names"]},{"isArrayAttr":{"Names":1},"attributes":["Start","End","Strand","Seq_id","Type","Source","Names","Id"]},{"isArrayAttr":{"Names":1},"attributes":["Start","End","Strand","Seq_id","Type","Source","Names","Id"]},{"isArrayAttr":{"Names":1},"attributes":["Start","End","Strand","Id","Names","Source","Type","Seq_id"]},{"attributes":["Start","End","Strand","Names","Id","Seq_id","Type","Source"],"isArrayAttr":{"Names":1}},{"isArrayAttr":{"Names":1},"attributes":["Start","End","Strand","Id","Names","Type","Source","Seq_id"]},{"attributes":["Start","End","Strand","Type","Source","Seq_id","Id","Names"],"isArrayAttr":{"Names":1}},{"isArrayAttr":{"Names":1},"attributes":["Start","End","Strand","Id","Names","Source","Type","Seq_id"]},{"attributes":["Start","End","Strand","Seq_id","Source","Type","Names","Id"],"isArrayAttr":{"Names":1}},{"isArrayAttr":{"Names":1},"attributes":["Start","End","Strand","Type","Source","Seq_id","Id","Names"]},{"attributes":["Start","End","Strand","Id","Names","Source","Type","Seq_id"],"isArrayAttr":{"Names":1}},{"attributes":["Start","End","Strand","Id","Names","Source","Type","Seq_id"],"isArrayAttr":{"Names":1}},{"attributes":["Start","End","Strand","Names","Id","Seq_id","Source","Type"],"isArrayAttr":{"Names":1}},{"attributes":["Start","End","Strand","Names","Id","Seq_id","Source","Type"],"isArrayAttr":{"Names":1}},{"attributes":["Start","End","Strand","Id","Names","Type","Source","Seq_id"],"isArrayAttr":{"Names":1}},{"isArrayAttr":{"Names":1},"attributes":["Start","End","Strand","Source","Type","Seq_id","Id","Names"]},{"attributes":["Start","End","Strand","Names","Id","Seq_id","Type","Source"],"isArrayAttr":{"Names":1}},{"attributes":["Start","End","Strand","Seq_id","Source","Type","Names","Id"],"isArrayAttr":{"Names":1}},{"isArrayAttr":{"Names":1},"attributes":["Start","End","Strand","Seq_id","Source","Type","Names","Id"]},{"attributes":["Start","End","Strand","Id","Names","Type","Source","Seq_id"],"isArrayAttr":{"Names":1}},{"attributes":["Start","End","Strand","Type","Source","Seq_id","Id","Names"],"isArrayAttr":{"Names":1}},{"attributes":["Start","End","Strand","Source","Type","Seq_id","Id","Names"],"isArrayAttr":{"Names":1}},{"isArrayAttr":{"Names":1},"attributes":["Start","End","Strand","Names","Id","Seq_id","Type","Source"]},{"isArrayAttr":{"Names":1},"attributes":["Start","End","Strand","Names","Id","Seq_id","Type","Source"]},{"attributes":["Start","End","Chunk"],"isArrayAttr":{"Sublist":1}}],"nclist":[[32,1346,3077880,1],[32,3079267,3657276,2]],"count":582,"maxEnd":3657276,"lazyClass":32,"urlTemplate":"lf-{Chunk}.json","minStart":1346}}