{"intervals":{"minStart":1346,"count":582,"maxEnd":3657276,"classes":[{"isArrayAttr":{"Names":1},"attributes":["Start","End","Strand","Names","Id","Type","Source","Seq_id"]},{"attributes":["Start","End","Strand","Source","Seq_id","Type","Id","Names"],"isArrayAttr":{"Names":1}},{"attributes":["Start","End","Strand","Names","Id","Type","Source","Seq_id"],"isArrayAttr":{"Names":1}},{"attributes":["Start","End","Strand","Names","Id","Type","Seq_id","Source"],"isArrayAttr":{"Names":1}},{"isArrayAttr":{"Names":1},"attributes":["Start","End","Strand","Names","Id","Type","Source","Seq_id"]},{"isArrayAttr":{"Names":1},"attributes":["Start","End","Strand","Names","Id","Type","Seq_id","Source"]},{"attributes":["Start","End","Strand","Seq_id","Source","Type","Id","Names"],"isArrayAttr":{"Names":1}},{"isArrayAttr":{"Names":1},"attributes":["Start","End","Strand","Seq_id","Source","Type","Id","Names"]},{"isArrayAttr":{"Names":1},"attributes":["Start","End","Strand","Source","Seq_id","Type","Id","Names"]},{"isArrayAttr":{"Names":1},"attributes":["Start","End","Strand","Id","Names","Source","Seq_id","Type"]},{"isArrayAttr":{"Names":1},"attributes":["Start","End","Strand","Seq_id","Source","Type","Id","Names"]},{"isArrayAttr":{"Names":1},"attributes":["Start","End","Strand","Type","Source","Seq_id","Names","Id"]},{"attributes":["Start","End","Strand","Id","Names","Seq_id","Source","Type"],"isArrayAttr":{"Names":1}},{"attributes":["Start","End","Strand","Names","Id","Type","Seq_id","Source"],"isArrayAttr":{"Names":1}},{"isArrayAttr":{"Names":1},"attributes":["Start","End","Strand","Names","Id","Type","Source","Seq_id"]},{"isArrayAttr":{"Names":1},"attributes":["Start","End","Strand","Type","Source","Seq_id","Names","Id"]},{"attributes":["Start","End","Strand","Type","Source","Seq_id","Names","Id"],"isArrayAttr":{"Names":1}},{"attributes":["Start","End","Strand","Names","Id","Type","Seq_id","Source"],"isArrayAttr":{"Names":1}},{"isArrayAttr":{"Names":1},"attributes":["Start","End","Strand","Seq_id","Source","Type","Id","Names"]},{"isArrayAttr":{"Names":1},"attributes":["Start","End","Strand","Names","Id","Type","Source","Seq_id"]},{"attributes":["Start","End","Strand","Type","Source","Seq_id","Names","Id"],"isArrayAttr":{"Names":1}},{"isArrayAttr":{"Names":1},"attributes":["Start","End","Strand","Seq_id","Source","Type","Id","Names"]},{"attributes":["Start","End","Strand","Type","Source","Seq_id","Names","Id"],"isArrayAttr":{"Names":1}},{"attributes":["Start","End","Strand","Id","Names","Source","Seq_id","Type"],"isArrayAttr":{"Names":1}},{"isArrayAttr":{"Names":1},"attributes":["Start","End","Strand","Type","Seq_id","Source","Names","Id"]},{"attributes":["Start","End","Strand","Id","Names","Source","Seq_id","Type"],"isArrayAttr":{"Names":1}},{"isArrayAttr":{"Names":1},"attributes":["Start","End","Strand","Type","Seq_id","Source","Names","Id"]},{"attributes":["Start","End","Strand","Names","Id","Type","Seq_id","Source"],"isArrayAttr":{"Names":1}},{"attributes":["Start","End","Strand","Source","Seq_id","Type","Id","Names"],"isArrayAttr":{"Names":1}},{"isArrayAttr":{"Names":1},"attributes":["Start","End","Strand","Type","Seq_id","Source","Names","Id"]},{"isArrayAttr":{"Names":1},"attributes":["Start","End","Strand","Id","Names","Seq_id","Source","Type"]},{"isArrayAttr":{"Names":1},"attributes":["Start","End","Strand","Names","Id","Type","Source","Seq_id"]},{"attributes":["Start","End","Strand","Type","Seq_id","Source","Names","Id"],"isArrayAttr":{"Names":1}},{"attributes":["Start","End","Strand","Source","Seq_id","Type","Id","Names"],"isArrayAttr":{"Names":1}},{"attributes":["Start","End","Strand","Id","Names","Source","Seq_id","Type"],"isArrayAttr":{"Names":1}},{"isArrayAttr":{"Names":1},"attributes":["Start","End","Strand","Names","Id","Type","Seq_id","Source"]},{"isArrayAttr":{"Names":1},"attributes":["Start","End","Strand","Type","Seq_id","Source","Names","Id"]},{"isArrayAttr":{"Names":1},"attributes":["Start","End","Strand","Id","Names","Seq_id","Source","Type"]},{"attributes":["Start","End","Strand","Source","Seq_id","Type","Id","Names"],"isArrayAttr":{"Names":1}},{"attributes":["Start","End","Strand","Id","Names","Source","Seq_id","Type"],"isArrayAttr":{"Names":1}},{"attributes":["Start","End","Strand","Id","Names","Seq_id","Source","Type"],"isArrayAttr":{"Names":1}},{"attributes":["Start","End","Strand","Type","Source","Seq_id","Names","Id"],"isArrayAttr":{"Names":1}},{"isArrayAttr":{"Names":1},"attributes":["Start","End","Strand","Source","Seq_id","Type","Id","Names"]},{"isArrayAttr":{"Names":1},"attributes":["Start","End","Strand","Id","Names","Seq_id","Source","Type"]},{"isArrayAttr":{"Names":1},"attributes":["Start","End","Strand","Id","Names","Source","Seq_id","Type"]},{"attributes":["Start","End","Strand","Id","Names","Seq_id","Source","Type"],"isArrayAttr":{"Names":1}},{"attributes":["Start","End","Strand","Type","Seq_id","Source","Names","Id"],"isArrayAttr":{"Names":1}},{"isArrayAttr":{"Names":1},"attributes":["Start","End","Strand","Seq_id","Source","Type","Id","Names"]},{"isArrayAttr":{"Sublist":1},"attributes":["Start","End","Chunk"]}],"nclist":[[48,1346,3073952,1],[48,3076322,3657276,2]],"lazyClass":48,"urlTemplate":"lf-{Chunk}.json"},"formatVersion":1,"featureCount":582,"histograms":{"stats":[{"basesPerBin":"20000","mean":3.53551912568306,"max":9},{"basesPerBin":"40000","max":11,"mean":6.67391304347826}],"meta":[{"arrayParams":{"urlTemplate":"hist-20000-{Chunk}.json","length":183,"chunkSize":10000},"basesPerBin":"20000"},{"basesPerBin":"40000","arrayParams":{"length":92,"chunkSize":10000,"urlTemplate":"hist-40000-{Chunk}.json"}}]}}